pfhb
