Metadata-Version: 2.1
Name: pfhb
Version: 0.9.5
Summary: Python package to dig hosts and generate PF (Packet Filter) rules
Home-page: https://github.com/ricardofalasca/packet-filter-host-blocker/
Author: Ricardo Falasca
Author-email: ricardo@falasca.com.br
License: MIT
Platform: UNKNOWN
Classifier: Development Status :: 5 - Production/Stable
Classifier: Intended Audience :: Developers
Classifier: Programming Language :: Python :: 3
Classifier: Topic :: Software Development :: Libraries :: Python Modules
